{"Symbol": "PH", "AssetType": "Common Stock", "Name": "Parker-Hannifin Corporation", "Description": "Parker-Hannifin Corporation, originally Parker Appliance Company, usually referred to as just Parker, is an American corporation specializing in motion and control technologies. Its corporate headquarters are in Mayfield Heights, Ohio, in Greater Cleveland.", "CIK": "76334", "Exchange": "NYSE", "Currency": "USD", "Country": "USA", "Sector": "MANUFACTURING", "Industry": "MISCELLANEOUS FABRICATED METAL PRODUCTS", "Address": "6035 PARKLAND BOULEVARD, CLEVELAND, OH, US", "FiscalYearEnd": "June", "LatestQuarter": "2021-09-30", "MarketCapitalization": "41971712000", "EBITDA": "3151611000", "PERatio": "22.77", "PEGRatio": "1.409", "BookValue": "66.07", "DividendPerShare": "3.82", "DividendYield": "0.0116", "EPS": "14.35", "RevenuePerShareTTM": "115.34", "ProfitMargin": "0.126", "OperatingMarginTTM": "0.172", "ReturnOnAssetsTTM": "0.0799", "ReturnOnEquityTTM": "0.25", "RevenueTTM": "14879909000", "GrossProfitTTM": "3932960000", "DilutedEPSTTM": "14.35", "QuarterlyEarningsGrowthYOY": "0.408", "QuarterlyRevenueGrowthYOY": "0.165", "AnalystTargetPrice": "368.19", "TrailingPE": "22.77", "ForwardPE": "18.69", "PriceToSalesRatioTTM": "2.821", "PriceToBookRatio": "4.991", "EVToRevenue": "3.254", "EVToEBITDA": "14.94", "Beta": "1.733", "52WeekHigh": "334.98", "52WeekLow": "244.22", "50DayMovingAverage": "301.32", "200DayMovingAverage": "302.93", "SharesOutstanding": "128515000", "DividendDate": "2021-12-03", "ExDividendDate": "2021-11-10"}